bytedance_eval_fc_api/__init__.py
bytedance_eval_fc_api-0.0.1.dist-info/METADATA
bytedance_eval_fc_api-0.0.1.dist-info/WHEEL
bytedance_eval_fc_api-0.0.1.dist-info/top_level.txt
bytedance_eval_fc_api-0.0.1.dist-info/RECORD
